mtsa/__init__.py
mtsa/common.py
mtsa/correlation_networks.py
mtsa/experiments.py
mtsa/metrics.py
mtsa/model_selection.py
mtsa/pipelines.py
mtsa/plotters.py
mtsa/training.py
mtsa/utils.py
mtsa/features/__init__.py
mtsa/features/mel.py
mtsa/features/stats.py
mtsa/models/__init__.py
mtsa/models/base.py
mtsa/models/gacvae.py
mtsa/models/ganf.py
mtsa/models/hitachi.py
mtsa/models/isolationforest.py
mtsa/models/mfccmix.py
mtsa/models/oneClassSVM.py
mtsa/models/ransyncorders.py
mtsa/models/transformer.py
mtsa/models/GANF_components/DROCC.py
mtsa/models/GANF_components/DeepSAD.py
mtsa/models/GANF_components/GAN.py
mtsa/models/GANF_components/NF.py
mtsa/models/GANF_components/RNN.py
mtsa/models/GANF_components/__init__.py
mtsa/models/GANF_components/gacvaeBaseModel.py
mtsa/models/GANF_components/ganfBaseModel.py
mtsa/models/GANF_components/ganfLayoutData.py
mtsa/models/GANF_components/gnn.py
mtsa/models/GANF_components/vae.py
mtsa/models/networkAnalysis/__init__.py
mtsa/models/networkAnalysis/networkLearnerModel.py
mtsa/models/networkAnalysis/networkLearnerModelResultOrchestrator.py
mtsa/models/networkAnalysis/networkLearnerObserver.py
mtsa/models/ransyncoders_components/__init__.py
mtsa/models/ransyncoders_components/decoder.py
mtsa/models/ransyncoders_components/encoder.py
mtsa/models/ransyncoders_components/frequencycoder.py
mtsa/models/ransyncoders_components/rancoders.py
mtsa/models/ransyncoders_components/ransyncoders_base.py
mtsa/models/ransyncoders_components/sinusoidalcoder.py
mtsa/models/ransyncoders_components/exceptions/__init__.py
mtsa/models/ransyncoders_components/exceptions/parametererror.py
mtsa/models/transformer_components/__init__.py
mtsa/models/transformer_components/attn.py
mtsa/models/transformer_components/decoder_layer.py
mtsa/models/transformer_components/embed.py
mtsa/models/transformer_components/encoder_layer.py
mtsa/models/transformer_components/multi_head_attention.py
mtsa/models/transformer_components/position_wise_feedforward.py
mtsa-0.2.4.dist-info/METADATA
mtsa-0.2.4.dist-info/WHEEL
mtsa-0.2.4.dist-info/top_level.txt
mtsa-0.2.4.dist-info/zip-safe
mtsa-0.2.4.dist-info/RECORD
