Metadata-Version: 2.4
Name: mtsa
Version: 0.2.4
Summary: Multiple Time Series Analysis
Home-page: https://github.com/diegompin/mtsa
Author: Diego Pinheiro
Author-email: diegompin@gmail.com
License: BSD 3-Clause License
Keywords: mtsa,setuptools
Classifier: License :: OSI Approved :: BSD License
Classifier: Programming Language :: Python :: 3
Requires-Dist: pandas==2.2.2
Requires-Dist: pytest==7.2.0
Requires-Dist: numpy==1.24.4
Requires-Dist: matplotlib==3.8.0
Requires-Dist: scipy==1.11.2
Requires-Dist: ipykernel==5.5.6
Requires-Dist: librosa==0.9.2
Requires-Dist: tensorflow==2.17.0
Requires-Dist: spectrum==0.6.8
Requires-Dist: torch==2.5.1
